selenol_account/__init__.py
selenol_account/config.py
selenol_account/exceptions.py
selenol_account/fixtures.py
selenol_account/models.py
selenol_account/params.py
selenol_account/serializers.py
selenol_account-0.1.dist-info/DESCRIPTION.rst
selenol_account-0.1.dist-info/METADATA
selenol_account-0.1.dist-info/RECORD
selenol_account-0.1.dist-info/WHEEL
selenol_account-0.1.dist-info/entry_points.txt
selenol_account-0.1.dist-info/metadata.json
selenol_account-0.1.dist-info/top_level.txt
