Metadata-Version: 2.0
Name: selenol-account
Version: 0.1
Summary: Selenol module to user related actions.
Home-page: https://github.com/selenol/selenol-account
Author: Javier Delgado
Author-email: JavierDelgado@outlook.com
License: GPLv3
Platform: UNKNOWN
Requires-Dist: requests (>=2.13.0)
Requires-Dist: selenol-platform (>=0.1)
Requires-Dist: selenol-python (>=0.1)
Requires-Dist: sqlalchemy (>=1.1.9)
Provides-Extra: tests
Requires-Dist: coverage (>=4.0); extra == 'tests'
Requires-Dist: isort (>=4.2.5); extra == 'tests'
Requires-Dist: mock (>=2.0.0); extra == 'tests'
Requires-Dist: pydocstyle (>=1.1.1); extra == 'tests'
Requires-Dist: pytest (>=3.0.7); extra == 'tests'
Requires-Dist: pytest-cache (>=1.0); extra == 'tests'
Requires-Dist: pytest-cov (>=2.4.0); extra == 'tests'
Requires-Dist: pytest-pep8 (>=1.0.6); extra == 'tests'
Requires-Dist: pytest-runner (>=2.11.1); extra == 'tests'
